polygon_math/__init__.py
polygon_math/polygon.py
polygon_math-1.3.3.dist-info/licenses/LICENSE
polygon_math-1.3.3.dist-info/METADATA
polygon_math-1.3.3.dist-info/WHEEL
polygon_math-1.3.3.dist-info/top_level.txt
polygon_math-1.3.3.dist-info/RECORD
