Metadata-Version: 2.4
Name: polygon_math
Version: 1.3.3
Summary: Calculate geometric properties of arbitrary 2D polygons
Home-page: https://github.com/gerritnowald/polygon
Author: Gerrit Nowald
Author-email: gerrit.nowald@gmail.com
Project-URL: Bug Tracker, https://github.com/gerritnowald/polygon/issues
Classifier: Programming Language :: Python :: 3
Classifier: License :: OSI Approved :: MIT License
Classifier: Operating System :: OS Independent
Requires-Python: >=3.6.15
License-File: LICENSE
Requires-Dist: numpy>=1.15.0
Requires-Dist: matplotlib>=2.0.0
Dynamic: license-file
